abjax/__init__.py
abjax/foo.py
abjax/api/__init__.py
abjax/config/__init__.py
abjax/core/__init__.py
abjax/core/corrections.py
abjax/core/cuped.py
abjax/core/stats.py
abjax/utils/__init__.py
abjax-0.0.1.dist-info/METADATA
abjax-0.0.1.dist-info/WHEEL
abjax-0.0.1.dist-info/RECORD
