Metadata-Version: 2.4
Name: abjax
Version: 0.0.1
Summary: High-performance Python library for AB testing analysis with JAX and FastAPI
Project-URL: Homepage, https://github.com/your-org/abjax
Project-URL: Documentation, https://abjax.readthedocs.io
Project-URL: Repository, https://github.com/your-org/abjax
Project-URL: Bug Tracker, https://github.com/your-org/abjax/issues
Author: ABJAX Team
License-Expression: MIT
Keywords: ab-testing,cuped,jax,statistics,variance-reduction
Classifier: Development Status :: 3 - Alpha
Classifier: Intended Audience :: Developers
Classifier: Intended Audience :: Science/Research
Classifier: License :: OSI Approved :: MIT License
Classifier: Operating System :: OS Independent
Classifier: Programming Language :: Python :: 3
Classifier: Programming Language :: Python :: 3.9
Classifier: Programming Language :: Python :: 3.10
Classifier: Programming Language :: Python :: 3.11
Classifier: Programming Language :: Python :: 3.12
Classifier: Topic :: Scientific/Engineering :: Information Analysis
Classifier: Topic :: Software Development :: Libraries :: Python Modules
Requires-Python: >=3.9
Requires-Dist: fastapi>=0.100.0
Requires-Dist: jax>=0.4.20
Requires-Dist: jaxlib>=0.4.20
Requires-Dist: matplotlib>=3.9.4
Requires-Dist: numpy>=1.24.0
Requires-Dist: pandas>=2.3.1
Requires-Dist: polars>=0.19.0
Requires-Dist: pydantic>=2.0
Requires-Dist: scipy>=1.10.0
Requires-Dist: seaborn>=0.13.2
Requires-Dist: uvicorn[standard]>=0.20.0
Provides-Extra: all
Requires-Dist: jupyter>=1.0; extra == 'all'
Requires-Dist: matplotlib>=3.6; extra == 'all'
Requires-Dist: myst-parser>=2.0; extra == 'all'
Requires-Dist: nbsphinx>=0.9; extra == 'all'
Requires-Dist: plotly>=5.0; extra == 'all'
Requires-Dist: seaborn>=0.12; extra == 'all'
Requires-Dist: sphinx-rtd-theme>=1.2; extra == 'all'
Requires-Dist: sphinx>=6.0; extra == 'all'
Provides-Extra: docs
Requires-Dist: myst-parser>=2.0; extra == 'docs'
Requires-Dist: nbsphinx>=0.9; extra == 'docs'
Requires-Dist: sphinx-rtd-theme>=1.2; extra == 'docs'
Requires-Dist: sphinx>=6.0; extra == 'docs'
Provides-Extra: jupyter
Requires-Dist: jupyter>=1.0; extra == 'jupyter'
Requires-Dist: matplotlib>=3.6; extra == 'jupyter'
Requires-Dist: plotly>=5.0; extra == 'jupyter'
Requires-Dist: seaborn>=0.12; extra == 'jupyter'
